tld/__init__.py
tld/base.py
tld/conf.py
tld/defaults.py
tld/exceptions.py
tld/helpers.py
tld/py.typed
tld/registry.py
tld/result.py
tld/trie.py
tld/utils.py
tld/res/effective_tld_names.dat.txt
tld/res/effective_tld_names_public_only.dat.txt
tld/tests/__init__.py
tld/tests/base.py
tld/tests/test_commands.py
tld/tests/test_core.py
tld/tests/test_registry.py
tld/tests/res/effective_tld_names_custom.dat.txt
tld-0.12.7.dist-info/LICENSE_LGPL_2.1.txt
tld-0.12.7.dist-info/METADATA
tld-0.12.7.dist-info/WHEEL
tld-0.12.7.dist-info/entry_points.txt
tld-0.12.7.dist-info/top_level.txt
tld-0.12.7.dist-info/RECORD
