Metadata-Version: 2.1
Name: tld
Version: 0.12.7
Summary: Extract the top-level domain (TLD) from the URL given.
Home-page: https://github.com/barseghyanartur/tld
Author: Artur Barseghyan
Author-email: artur.barseghyan@gmail.com
License: MPL-1.1 OR GPL-2.0-only OR LGPL-2.1-or-later
Project-URL: Bug Tracker, https://github.com/barseghyanartur/tld/issues
Project-URL: Documentation, https://tld.readthedocs.io/
Project-URL: Source Code, https://github.com/barseghyanartur/tld/
Project-URL: Changelog, https://tld.readthedocs.io/en/latest/changelog.html
Keywords: tld,top-level domain names,python
Classifier: Programming Language :: Python
Classifier: Programming Language :: Python :: 2
Classifier: Programming Language :: Python :: 2.7
Classifier: Programming Language :: Python :: 3
Classifier: Programming Language :: Python :: 3.5
Classifier: Programming Language :: Python :: 3.6
Classifier: Programming Language :: Python :: 3.7
Classifier: Programming Language :: Python :: 3.8
Classifier: Programming Language :: Python :: 3.9
Classifier: Programming Language :: Python :: 3.10
Classifier: Programming Language :: Python :: 3.11
Classifier: Environment :: Web Environment
Classifier: Intended Audience :: Developers
Classifier: Operating System :: OS Independent
Classifier: Development Status :: 5 - Production/Stable
Classifier: Topic :: Internet
Classifier: License :: OSI Approved :: Mozilla Public License 1.1 (MPL 1.1)
Classifier: License :: OSI Approved :: GNU General Public License v2 (GPLv2)
Classifier: License :: OSI Approved :: GNU Lesser General Public License v2 or later (LGPLv2+)
Requires-Python: >=2.7, <4
License-File: LICENSE_LGPL_2.1.txt
